{
    "get": "standings",
    "parameters": {
        "league": "40",
        "season": "2023"
    },
    "errors": [],
    "results": 1,
    "paging": {
        "current": 1,
        "total": 1
    },
    "response": [
        {
            "league": {
                "id": 40,
                "name": "Championship",
                "country": "England",
                "logo": "https://media.api-sports.io/football/leagues/40.png",
                "flag": "https://media.api-sports.io/flags/gb.svg",
                "season": 2023,
                "standings": [
                    [
                        {
                            "rank": 1,
                            "team": {
                                "id": 46,
                                "name": "Leicester",
                                "logo": "https://media.api-sports.io/football/teams/46.png"
                            },
                            "points": 97,
                            "goalsDiff": 48,
                            "group": "Championship",
                            "form": "LWWWL",
                            "status": "same",
                            "description": "Promotion - Premier League",
                            "all": {
                                "played": 46,
                                "win": 31,
                                "draw": 4,
                                "lose": 11,
                                "goals": {
                                    "for": 89,
                                    "against": 41
                                }
                            },
                            "home": {
                                "played": 23,
                                "win": 17,
                                "draw": 1,
                                "lose": 5,
                                "goals": {
                                    "for": 47,
                                    "against": 18
                                }
                            },
                            "away": {
                                "played": 23,
                                "win": 14,
                                "draw": 3,
                                "lose": 6,
                                "goals": {
                                    "for": 42,
                                    "against": 23
                                }
                            },
                            "update": "2024-05-29T00:00:00+00:00"
                        },
                        {
                            "rank": 2,
                            "team": {
                                "id": 57,
                                "name": "Ipswich",
                                "logo": "https://media.api-sports.io/football/teams/57.png"
                            },
                            "points": 96,
                            "goalsDiff": 35,
                            "group": "Championship",
                            "form": "WWDDD",
                            "status": "same",
                            "description": "Promotion - Premier League",
                            "all": {
                                "played": 46,
                                "win": 28,
                                "draw": 12,
                                "lose": 6,
                                "goals": {
                                    "for": 92,
                                    "against": 57
                                }
                            },
                            "home": {
                                "played": 23,
                                "win": 16,
                                "draw": 6,
                                "lose": 1,
                                "goals": {
                                    "for": 59,
                                    "against": 32
                                }
                            },
                            "away": {
                                "played": 23,
                                "win": 12,
                                "draw": 6,
                                "lose": 5,
                                "goals": {
                                    "for": 33,
                                    "against": 25
                                }
                            },
                            "update": "2024-05-29T00:00:00+00:00"
                        },
                        {
                            "rank": 3,
                            "team": {
                                "id": 63,
                                "name": "Leeds",
                                "logo": "https://media.api-sports.io/football/teams/63.png"
                            },
                            "points": 90,
                            "goalsDiff": 38,
                            "group": "Championship",
                            "form": "LLWLD",
                            "status": "same",
                            "description": "Promotion - Championship (Play Offs: Semi-finals)",
                            "all": {
                                "played": 46,
                                "win": 27,
                                "draw": 9,
                                "lose": 10,
                                "goals": {
                                    "for": 81,
                                    "against": 43
                                }
                            },
                            "home": {
                                "played": 23,
                                "win": 16,
                                "draw": 5,
                                "lose": 2,
                                "goals": {
                                    "for": 45,
                                    "against": 16
                                }
                            },
                            "away": {
                                "played": 23,
                                "win": 11,
                                "draw": 4,
                                "lose": 8,
                                "goals": {
                                    "for": 36,
                                    "against": 27
                                }
                            },
                            "update": "2024-05-29T00:00:00+00:00"
                        },
                        {
                            "rank": 4,
                            "team": {
                                "id": 41,
                                "name": "Southampton",
                                "logo": "https://media.api-sports.io/football/teams/41.png"
                            },
                            "points": 87,
                            "goalsDiff": 24,
                            "group": "Championship",
                            "form": "WLLLW",
                            "status": "same",
                            "description": "Promotion - Championship (Play Offs: Semi-finals)",
                            "all": {
                                "played": 46,
                                "win": 26,
                                "draw": 9,
                                "lose": 11,
                                "goals": {
                                    "for": 87,
                                    "against": 63
                                }
                            },
                            "home": {
                                "played": 23,
                                "win": 15,
                                "draw": 3,
                                "lose": 5,
                                "goals": {
                                    "for": 54,
                                    "against": 29
                                }
                            },
                            "away": {
                                "played": 23,
                                "win": 11,
                                "draw": 6,
                                "lose": 6,
                                "goals": {
                                    "for": 33,
                                    "against": 34
                                }
                            },
                            "update": "2024-05-29T00:00:00+00:00"
                        },
                        {
                            "rank": 5,
                            "team": {
                                "id": 60,
                                "name": "West Brom",
                                "logo": "https://media.api-sports.io/football/teams/60.png"
                            },
                            "points": 75,
                            "goalsDiff": 23,
                            "group": "Championship",
                            "form": "WLLLW",
                            "status": "same",
                            "description": "Promotion - Championship (Play Offs: Semi-finals)",
                            "all": {
                                "played": 46,
                                "win": 21,
                                "draw": 12,
                                "lose": 13,
                                "goals": {
                                    "for": 70,
                                    "against": 47
                                }
                            },
                            "home": {
                                "played": 23,
                                "win": 15,
                                "draw": 4,
                                "lose": 4,
                                "goals": {
                                    "for": 38,
                                    "against": 17
                                }
                            },
                            "away": {
                                "played": 23,
                                "win": 6,
                                "draw": 8,
                                "lose": 9,
                                "goals": {
                                    "for": 32,
                                    "against": 30
                                }
                            },
                            "update": "2024-05-29T00:00:00+00:00"
                        },
                        {
                            "rank": 6,
                            "team": {
                                "id": 71,
                                "name": "Norwich",
                                "logo": "https://media.api-sports.io/football/teams/71.png"
                            },
                            "points": 73,
                            "goalsDiff": 15,
                            "group": "Championship",
                            "form": "LDDWD",
                            "status": "same",
                            "description": "Promotion - Championship (Play Offs: Semi-finals)",
                            "all": {
                                "played": 46,
                                "win": 21,
                                "draw": 10,
                                "lose": 15,
                                "goals": {
                                    "for": 79,
                                    "against": 64
                                }
                            },
                            "home": {
                                "played": 23,
                                "win": 15,
                                "draw": 4,
                                "lose": 4,
                                "goals": {
                                    "for": 43,
                                    "against": 22
                                }
                            },
                            "away": {
                                "played": 23,
                                "win": 6,
                                "draw": 6,
                                "lose": 11,
                                "goals": {
                                    "for": 36,
                                    "against": 42
                                }
                            },
                            "update": "2024-05-29T00:00:00+00:00"
                        },
                        {
                            "rank": 7,
                            "team": {
                                "id": 64,
                                "name": "Hull City",
                                "logo": "https://media.api-sports.io/football/teams/64.png"
                            },
                            "points": 70,
                            "goalsDiff": 8,
                            "group": "Championship",
                            "form": "LDWDW",
                            "status": "same",
                            "description": null,
                            "all": {
                                "played": 46,
                                "win": 19,
                                "draw": 13,
                                "lose": 14,
                                "goals": {
                                    "for": 68,
                                    "against": 60
                                }
                            },
                            "home": {
                                "played": 23,
                                "win": 8,
                                "draw": 9,
                                "lose": 6,
                                "goals": {
                                    "for": 35,
                                    "against": 27
                                }
                            },
                            "away": {
                                "played": 23,
                                "win": 11,
                                "draw": 4,
                                "lose": 8,
                                "goals": {
                                    "for": 33,
                                    "against": 33
                                }
                            },
                            "update": "2024-05-29T00:00:00+00:00"
                        },
                        {
                            "rank": 8,
                            "team": {
                                "id": 70,
                                "name": "Middlesbrough",
                                "logo": "https://media.api-sports.io/football/teams/70.png"
                            },
                            "points": 69,
                            "goalsDiff": 9,
                            "group": "Championship",
                            "form": "WWLDD",
                            "status": "same",
                            "description": null,
                            "all": {
                                "played": 46,
                                "win": 20,
                                "draw": 9,
                                "lose": 17,
                                "goals": {
                                    "for": 71,
                                    "against": 62
                                }
                            },
                            "home": {
                                "played": 23,
                                "win": 10,
                                "draw": 4,
                                "lose": 9,
                                "goals": {
                                    "for": 30,
                                    "against": 26
                                }
                            },
                            "away": {
                                "played": 23,
                                "win": 10,
                                "draw": 5,
                                "lose": 8,
                                "goals": {
                                    "for": 41,
                                    "against": 36
                                }
                            },
                            "update": "2024-05-29T00:00:00+00:00"
                        },
                        {
                            "rank": 9,
                            "team": {
                                "id": 1346,
                                "name": "Coventry",
                                "logo": "https://media.api-sports.io/football/teams/1346.png"
                            },
                            "points": 64,
                            "goalsDiff": 11,
                            "group": "Championship",
                            "form": "LLDLL",
                            "status": "same",
                            "description": null,
                            "all": {
                                "played": 46,
                                "win": 17,
                                "draw": 13,
                                "lose": 16,
                                "goals": {
                                    "for": 70,
                                    "against": 59
                                }
                            },
                            "home": {
                                "played": 23,
                                "win": 9,
                                "draw": 8,
                                "lose": 6,
                                "goals": {
                                    "for": 36,
                                    "against": 27
                                }
                            },
                            "away": {
                                "played": 23,
                                "win": 8,
                                "draw": 5,
                                "lose": 10,
                                "goals": {
                                    "for": 34,
                                    "against": 32
                                }
                            },
                            "update": "2024-05-29T00:00:00+00:00"
                        },
                        {
                            "rank": 10,
                            "team": {
                                "id": 59,
                                "name": "Preston",
                                "logo": "https://media.api-sports.io/football/teams/59.png"
                            },
                            "points": 63,
                            "goalsDiff": -11,
                            "group": "Championship",
                            "form": "LLLLL",
                            "status": "same",
                            "description": null,
                            "all": {
                                "played": 46,
                                "win": 18,
                                "draw": 9,
                                "lose": 19,
                                "goals": {
                                    "for": 56,
                                    "against": 67
                                }
                            },
                            "home": {
                                "played": 23,
                                "win": 11,
                                "draw": 4,
                                "lose": 8,
                                "goals": {
                                    "for": 35,
                                    "against": 36
                                }
                            },
                            "away": {
                                "played": 23,
                                "win": 7,
                                "draw": 5,
                                "lose": 11,
                                "goals": {
                                    "for": 21,
                                    "against": 31
                                }
                            },
                            "update": "2024-05-29T00:00:00+00:00"
                        },
                        {
                            "rank": 11,
                            "team": {
                                "id": 56,
                                "name": "Bristol City",
                                "logo": "https://media.api-sports.io/football/teams/56.png"
                            },
                            "points": 62,
                            "goalsDiff": 2,
                            "group": "Championship",
                            "form": "LWDDW",
                            "status": "same",
                            "description": null,
                            "all": {
                                "played": 46,
                                "win": 17,
                                "draw": 11,
                                "lose": 18,
                                "goals": {
                                    "for": 53,
                                    "against": 51
                                }
                            },
                            "home": {
                                "played": 23,
                                "win": 11,
                                "draw": 4,
                                "lose": 8,
                                "goals": {
                                    "for": 31,
                                    "against": 21
                                }
                            },
                            "away": {
                                "played": 23,
                                "win": 6,
                                "draw": 7,
                                "lose": 10,
                                "goals": {
                                    "for": 22,
                                    "against": 30
                                }
                            },
                            "update": "2024-05-29T00:00:00+00:00"
                        },
                        {
                            "rank": 12,
                            "team": {
                                "id": 43,
                                "name": "Cardiff",
                                "logo": "https://media.api-sports.io/football/teams/43.png"
                            },
                            "points": 62,
                            "goalsDiff": -17,
                            "group": "Championship",
                            "form": "LLWLW",
                            "status": "same",
                            "description": null,
                            "all": {
                                "played": 46,
                                "win": 19,
                                "draw": 5,
                                "lose": 22,
                                "goals": {
                                    "for": 53,
                                    "against": 70
                                }
                            },
                            "home": {
                                "played": 23,
                                "win": 10,
                                "draw": 3,
                                "lose": 10,
                                "goals": {
                                    "for": 27,
                                    "against": 32
                                }
                            },
                            "away": {
                                "played": 23,
                                "win": 9,
                                "draw": 2,
                                "lose": 12,
                                "goals": {
                                    "for": 26,
                                    "against": 38
                                }
                            },
                            "update": "2024-05-29T00:00:00+00:00"
                        },
                        {
                            "rank": 13,
                            "team": {
                                "id": 58,
                                "name": "Millwall",
                                "logo": "https://media.api-sports.io/football/teams/58.png"
                            },
                            "points": 59,
                            "goalsDiff": -10,
                            "group": "Championship",
                            "form": "WWWWW",
                            "status": "same",
                            "description": null,
                            "all": {
                                "played": 46,
                                "win": 16,
                                "draw": 11,
                                "lose": 19,
                                "goals": {
                                    "for": 45,
                                    "against": 55
                                }
                            },
                            "home": {
                                "played": 23,
                                "win": 9,
                                "draw": 5,
                                "lose": 9,
                                "goals": {
                                    "for": 22,
                                    "against": 29
                                }
                            },
                            "away": {
                                "played": 23,
                                "win": 7,
                                "draw": 6,
                                "lose": 10,
                                "goals": {
                                    "for": 23,
                                    "against": 26
                                }
                            },
                            "update": "2024-05-29T00:00:00+00:00"
                        },
                        {
                            "rank": 14,
                            "team": {
                                "id": 76,
                                "name": "Swansea",
                                "logo": "https://media.api-sports.io/football/teams/76.png"
                            },
                            "points": 57,
                            "goalsDiff": -6,
                            "group": "Championship",
                            "form": "LDWWW",
                            "status": "same",
                            "description": null,
                            "all": {
                                "played": 46,
                                "win": 15,
                                "draw": 12,
                                "lose": 19,
                                "goals": {
                                    "for": 59,
                                    "against": 65
                                }
                            },
                            "home": {
                                "played": 23,
                                "win": 8,
                                "draw": 5,
                                "lose": 10,
                                "goals": {
                                    "for": 26,
                                    "against": 28
                                }
                            },
                            "away": {
                                "played": 23,
                                "win": 7,
                                "draw": 7,
                                "lose": 9,
                                "goals": {
                                    "for": 33,
                                    "against": 37
                                }
                            },
                            "update": "2024-05-29T00:00:00+00:00"
                        },
                        {
                            "rank": 15,
                            "team": {
                                "id": 38,
                                "name": "Watford",
                                "logo": "https://media.api-sports.io/football/teams/38.png"
                            },
                            "points": 56,
                            "goalsDiff": 0,
                            "group": "Championship",
                            "form": "LWDLD",
                            "status": "same",
                            "description": null,
                            "all": {
                                "played": 46,
                                "win": 13,
                                "draw": 17,
                                "lose": 16,
                                "goals": {
                                    "for": 61,
                                    "against": 61
                                }
                            },
                            "home": {
                                "played": 23,
                                "win": 6,
                                "draw": 9,
                                "lose": 8,
                                "goals": {
                                    "for": 32,
                                    "against": 28
                                }
                            },
                            "away": {
                                "played": 23,
                                "win": 7,
                                "draw": 8,
                                "lose": 8,
                                "goals": {
                                    "for": 29,
                                    "against": 33
                                }
                            },
                            "update": "2024-05-29T00:00:00+00:00"
                        },
                        {
                            "rank": 16,
                            "team": {
                                "id": 746,
                                "name": "Sunderland",
                                "logo": "https://media.api-sports.io/football/teams/746.png"
                            },
                            "points": 56,
                            "goalsDiff": -2,
                            "group": "Championship",
                            "form": "LLLWD",
                            "status": "same",
                            "description": null,
                            "all": {
                                "played": 46,
                                "win": 16,
                                "draw": 8,
                                "lose": 22,
                                "goals": {
                                    "for": 52,
                                    "against": 54
                                }
                            },
                            "home": {
                                "played": 23,
                                "win": 10,
                                "draw": 2,
                                "lose": 11,
                                "goals": {
                                    "for": 30,
                                    "against": 30
                                }
                            },
                            "away": {
                                "played": 23,
                                "win": 6,
                                "draw": 6,
                                "lose": 11,
                                "goals": {
                                    "for": 22,
                                    "against": 24
                                }
                            },
                            "update": "2024-05-29T00:00:00+00:00"
                        },
                        {
                            "rank": 17,
                            "team": {
                                "id": 75,
                                "name": "Stoke City",
                                "logo": "https://media.api-sports.io/football/teams/75.png"
                            },
                            "points": 56,
                            "goalsDiff": -11,
                            "group": "Championship",
                            "form": "WWWDL",
                            "status": "same",
                            "description": null,
                            "all": {
                                "played": 46,
                                "win": 15,
                                "draw": 11,
                                "lose": 20,
                                "goals": {
                                    "for": 49,
                                    "against": 60
                                }
                            },
                            "home": {
                                "played": 23,
                                "win": 8,
                                "draw": 6,
                                "lose": 9,
                                "goals": {
                                    "for": 24,
                                    "against": 27
                                }
                            },
                            "away": {
                                "played": 23,
                                "win": 7,
                                "draw": 5,
                                "lose": 11,
                                "goals": {
                                    "for": 25,
                                    "against": 33
                                }
                            },
                            "update": "2024-05-29T00:00:00+00:00"
                        },
                        {
                            "rank": 18,
                            "team": {
                                "id": 72,
                                "name": "QPR",
                                "logo": "https://media.api-sports.io/football/teams/72.png"
                            },
                            "points": 56,
                            "goalsDiff": -11,
                            "group": "Championship",
                            "form": "WWWLD",
                            "status": "same",
                            "description": null,
                            "all": {
                                "played": 46,
                                "win": 15,
                                "draw": 11,
                                "lose": 20,
                                "goals": {
                                    "for": 47,
                                    "against": 58
                                }
                            },
                            "home": {
                                "played": 23,
                                "win": 7,
                                "draw": 6,
                                "lose": 10,
                                "goals": {
                                    "for": 28,
                                    "against": 32
                                }
                            },
                            "away": {
                                "played": 23,
                                "win": 8,
                                "draw": 5,
                                "lose": 10,
                                "goals": {
                                    "for": 19,
                                    "against": 26
                                }
                            },
                            "update": "2024-05-29T00:00:00+00:00"
                        },
                        {
                            "rank": 19,
                            "team": {
                                "id": 67,
                                "name": "Blackburn",
                                "logo": "https://media.api-sports.io/football/teams/67.png"
                            },
                            "points": 53,
                            "goalsDiff": -14,
                            "group": "Championship",
                            "form": "WDLWL",
                            "status": "same",
                            "description": null,
                            "all": {
                                "played": 46,
                                "win": 14,
                                "draw": 11,
                                "lose": 21,
                                "goals": {
                                    "for": 60,
                                    "against": 74
                                }
                            },
                            "home": {
                                "played": 23,
                                "win": 6,
                                "draw": 7,
                                "lose": 10,
                                "goals": {
                                    "for": 27,
                                    "against": 34
                                }
                            },
                            "away": {
                                "played": 23,
                                "win": 8,
                                "draw": 4,
                                "lose": 11,
                                "goals": {
                                    "for": 33,
                                    "against": 40
                                }
                            },
                            "update": "2024-05-29T00:00:00+00:00"
                        },
                        {
                            "rank": 20,
                            "team": {
                                "id": 74,
                                "name": "Sheffield Wednesday",
                                "logo": "https://media.api-sports.io/football/teams/74.png"
                            },
                            "points": 53,
                            "goalsDiff": -24,
                            "group": "Championship",
                            "form": "WWWDD",
                            "status": "same",
                            "description": null,
                            "all": {
                                "played": 46,
                                "win": 15,
                                "draw": 8,
                                "lose": 23,
                                "goals": {
                                    "for": 44,
                                    "against": 68
                                }
                            },
                            "home": {
                                "played": 23,
                                "win": 8,
                                "draw": 7,
                                "lose": 8,
                                "goals": {
                                    "for": 27,
                                    "against": 27
                                }
                            },
                            "away": {
                                "played": 23,
                                "win": 7,
                                "draw": 1,
                                "lose": 15,
                                "goals": {
                                    "for": 17,
                                    "against": 41
                                }
                            },
                            "update": "2024-05-29T00:00:00+00:00"
                        },
                        {
                            "rank": 21,
                            "team": {
                                "id": 1357,
                                "name": "Plymouth",
                                "logo": "https://media.api-sports.io/football/teams/1357.png"
                            },
                            "points": 51,
                            "goalsDiff": -11,
                            "group": "Championship",
                            "form": "WLLWD",
                            "status": "same",
                            "description": null,
                            "all": {
                                "played": 46,
                                "win": 13,
                                "draw": 12,
                                "lose": 21,
                                "goals": {
                                    "for": 59,
                                    "against": 70
                                }
                            },
                            "home": {
                                "played": 23,
                                "win": 10,
                                "draw": 5,
                                "lose": 8,
                                "goals": {
                                    "for": 41,
                                    "against": 35
                                }
                            },
                            "away": {
                                "played": 23,
                                "win": 3,
                                "draw": 7,
                                "lose": 13,
                                "goals": {
                                    "for": 18,
                                    "against": 35
                                }
                            },
                            "update": "2024-05-29T00:00:00+00:00"
                        },
                        {
                            "rank": 22,
                            "team": {
                                "id": 54,
                                "name": "Birmingham",
                                "logo": "https://media.api-sports.io/football/teams/54.png"
                            },
                            "points": 50,
                            "goalsDiff": -15,
                            "group": "Championship",
                            "form": "WDDWL",
                            "status": "same",
                            "description": "Relegation - League One",
                            "all": {
                                "played": 46,
                                "win": 13,
                                "draw": 11,
                                "lose": 22,
                                "goals": {
                                    "for": 50,
                                    "against": 65
                                }
                            },
                            "home": {
                                "played": 23,
                                "win": 10,
                                "draw": 6,
                                "lose": 7,
                                "goals": {
                                    "for": 31,
                                    "against": 25
                                }
                            },
                            "away": {
                                "played": 23,
                                "win": 3,
                                "draw": 5,
                                "lose": 15,
                                "goals": {
                                    "for": 19,
                                    "against": 40
                                }
                            },
                            "update": "2024-05-29T00:00:00+00:00"
                        },
                        {
                            "rank": 23,
                            "team": {
                                "id": 37,
                                "name": "Huddersfield",
                                "logo": "https://media.api-sports.io/football/teams/37.png"
                            },
                            "points": 45,
                            "goalsDiff": -29,
                            "group": "Championship",
                            "form": "LDLDL",
                            "status": "same",
                            "description": "Relegation - League One",
                            "all": {
                                "played": 46,
                                "win": 9,
                                "draw": 18,
                                "lose": 19,
                                "goals": {
                                    "for": 48,
                                    "against": 77
                                }
                            },
                            "home": {
                                "played": 23,
                                "win": 6,
                                "draw": 8,
                                "lose": 9,
                                "goals": {
                                    "for": 26,
                                    "against": 36
                                }
                            },
                            "away": {
                                "played": 23,
                                "win": 3,
                                "draw": 10,
                                "lose": 10,
                                "goals": {
                                    "for": 22,
                                    "against": 41
                                }
                            },
                            "update": "2024-05-29T00:00:00+00:00"
                        },
                        {
                            "rank": 24,
                            "team": {
                                "id": 73,
                                "name": "Rotherham",
                                "logo": "https://media.api-sports.io/football/teams/73.png"
                            },
                            "points": 27,
                            "goalsDiff": -52,
                            "group": "Championship",
                            "form": "WLDLL",
                            "status": "same",
                            "description": "Relegation - League One",
                            "all": {
                                "played": 46,
                                "win": 5,
                                "draw": 12,
                                "lose": 29,
                                "goals": {
                                    "for": 37,
                                    "against": 89
                                }
                            },
                            "home": {
                                "played": 23,
                                "win": 5,
                                "draw": 8,
                                "lose": 10,
                                "goals": {
                                    "for": 24,
                                    "against": 28
                                }
                            },
                            "away": {
                                "played": 23,
                                "win": 0,
                                "draw": 4,
                                "lose": 19,
                                "goals": {
                                    "for": 13,
                                    "against": 61
                                }
                            },
                            "update": "2024-05-29T00:00:00+00:00"
                        }
                    ]
                ]
            }
        }
    ]
}